covalent/__init__.py
covalent/covalent_client.py
covalent/services/__init__.py
covalent/services/balance_service.py
covalent/services/base_service.py
covalent/services/nft_service.py
covalent/services/pricing_service.py
covalent/services/security_service.py
covalent/services/transaction_service.py
covalent/services/xyk_service.py
covalent/services/util/__init__.py
covalent/services/util/api_helper.py
covalent/services/util/api_key_validator.py
covalent/services/util/back_off.py
covalent/services/util/calculate_pretty_balance.py
covalent/services/util/chains.py
covalent/services/util/debugger.py
covalent/services/util/prettify_currency.py
covalent/services/util/types.py
covalent_api_sdk-1.0.2.dist-info/METADATA
covalent_api_sdk-1.0.2.dist-info/WHEEL
covalent_api_sdk-1.0.2.dist-info/top_level.txt
covalent_api_sdk-1.0.2.dist-info/RECORD
