Metadata-Version: 2.1
Name: covalent-api-sdk
Version: 1.0.2
Summary: covalent-api-sdk-py
Home-page: https://github.com/covalenthq/covalent-api-sdk-py/
Author: Covalenthq
License: MIT
Classifier: Development Status :: 3 - Alpha
Classifier: Intended Audience :: Developers
Classifier: License :: OSI Approved :: MIT License
Classifier: Programming Language :: Python :: 3.7
Classifier: Programming Language :: Python :: 3.8
Classifier: Programming Language :: Python :: 3.9
Classifier: Programming Language :: Python :: 3.10
Classifier: Programming Language :: Python :: 3.11
Requires-Python: >=3.7
Requires-Dist: aiohttp
Requires-Dist: pytest
Requires-Dist: requests
Requires-Dist: pytest-env
Requires-Dist: pytest-asyncio
Requires-Dist: deprecated
